LICENSE.txt
README.md
setup.cfg
setup.py
PyBioMed/Pydna.py
PyBioMed/Pyinteraction.py
PyBioMed/Pymolecule.py
PyBioMed/Pyprotein.py
PyBioMed/__init__.py
PyBioMed.egg-info/PKG-INFO
PyBioMed.egg-info/SOURCES.txt
PyBioMed.egg-info/dependency_links.txt
PyBioMed.egg-info/not-zip-safe
PyBioMed.egg-info/requires.txt
PyBioMed.egg-info/top_level.txt
PyBioMed/PyDNA/1atp.pdb
PyBioMed/PyDNA/1efz.pdb
PyBioMed/PyDNA/1f88.pdb
PyBioMed/PyDNA/PyDNA.py
PyBioMed/PyDNA/PyDNAac.py
PyBioMed/PyDNA/PyDNAacutil.py
PyBioMed/PyDNA/PyDNAnac.py
PyBioMed/PyDNA/PyDNAnacutil.py
PyBioMed/PyDNA/PyDNApsenac.py
PyBioMed/PyDNA/PyDNApsenacutil.py
PyBioMed/PyDNA/PyDNAutil.py
PyBioMed/PyDNA/__init__.py
PyBioMed/PyDNA/mmc3.data
PyBioMed/PyDNA/mmc4.data
PyBioMed/PyGetMol/1atp.ent.gz
PyBioMed/PyGetMol/1atp.pdb
PyBioMed/PyGetMol/1efz.ent.gz
PyBioMed/PyGetMol/1efz.pdb
PyBioMed/PyGetMol/1f88.ent.gz
PyBioMed/PyGetMol/1f88.pdb
PyBioMed/PyGetMol/GetDNA.py
PyBioMed/PyGetMol/GetProtein.py
PyBioMed/PyGetMol/Getmol.py
PyBioMed/PyGetMol/__init__.py
PyBioMed/PyInteraction/PyInteraction.py
PyBioMed/PyInteraction/__init__.py
PyBioMed/PyMolecule/AtomProperty.py
PyBioMed/PyMolecule/AtomTypes.py
PyBioMed/PyMolecule/Crippen.txt
PyBioMed/PyMolecule/MinimalFeatures.fdef
PyBioMed/PyMolecule/PubChemFingerprints.py
PyBioMed/PyMolecule/Scaffolds.py
PyBioMed/PyMolecule/__init__.py
PyBioMed/PyMolecule/basak.py
PyBioMed/PyMolecule/bcut.py
PyBioMed/PyMolecule/cats2d.py
PyBioMed/PyMolecule/charge.py
PyBioMed/PyMolecule/connectivity.py
PyBioMed/PyMolecule/constitution.py
PyBioMed/PyMolecule/estate.py
PyBioMed/PyMolecule/fingerprint.py
PyBioMed/PyMolecule/geary.py
PyBioMed/PyMolecule/ghosecrippen.py
PyBioMed/PyMolecule/kappa.py
PyBioMed/PyMolecule/moe.py
PyBioMed/PyMolecule/molproperty.py
PyBioMed/PyMolecule/moran.py
PyBioMed/PyMolecule/moreaubroto.py
PyBioMed/PyMolecule/topology.py
PyBioMed/PyPretreat/PyDNAutil.py
PyBioMed/PyPretreat/PyPreTools.py
PyBioMed/PyPretreat/PyPretreatDNA.py
PyBioMed/PyPretreat/PyPretreatMol.py
PyBioMed/PyPretreat/PyPretreatMolutil.py
PyBioMed/PyPretreat/PyPretreatPro.py
PyBioMed/PyPretreat/__init__.py
PyBioMed/PyProtein/AAComposition.py
PyBioMed/PyProtein/AAIndex.py
